odoo8_addon_web_action_conditionable-8.0.0.1.0-py2.7-nspkg.pth
odoo_addons/web_action_conditionable/__openerp__.py
odoo_addons/web_action_conditionable/__init__.py
odoo_addons/web_action_conditionable/README.rst
odoo_addons/web_action_conditionable/views/view.xml
odoo_addons/web_action_conditionable/static/description/icon.png
odoo_addons/web_action_conditionable/static/src/js/views.js
odoo8_addon_web_action_conditionable-8.0.0.1.0.dist-info/top_level.txt
odoo8_addon_web_action_conditionable-8.0.0.1.0.dist-info/WHEEL
odoo8_addon_web_action_conditionable-8.0.0.1.0.dist-info/RECORD
odoo8_addon_web_action_conditionable-8.0.0.1.0.dist-info/metadata.json
odoo8_addon_web_action_conditionable-8.0.0.1.0.dist-info/DESCRIPTION.rst
odoo8_addon_web_action_conditionable-8.0.0.1.0.dist-info/METADATA
odoo8_addon_web_action_conditionable-8.0.0.1.0.dist-info/namespace_packages.txt
